wimlib/__init__.py
wimlib/_global.py
wimlib/backend.py
wimlib/compression.py
wimlib/error.py
wimlib/file.py
wimlib/image.py
wimlib/info.py
wimlib/progress.py
python_wimlib-0.1.0.dist-info/LICENSE
python_wimlib-0.1.0.dist-info/METADATA
python_wimlib-0.1.0.dist-info/WHEEL
python_wimlib-0.1.0.dist-info/top_level.txt
python_wimlib-0.1.0.dist-info/RECORD
