Metadata-Version: 2.1
Name: python-wimlib
Version: 0.1.0
Summary: Python bindings for wimlib (unofficial)
Home-page: https://github.com/0xgiddi/python-wimlib
Author: Gideon S. (0xGiddi)
Author-email: elmocia@gmail.com
License: GPLv3
Classifier: Intended Audience :: Developers
License-File: LICENSE
Requires-Dist: cffi >=1.8.2
